romeways/__init__.py
romeways/src/__init__.py
romeways/src/core/__init__.py
romeways/src/core/abstract/__init__.py
romeways/src/core/abstract/infrastructure/__init__.py
romeways/src/core/abstract/infrastructure/queue_connector/__init__.py
romeways/src/core/abstract/infrastructure/queue_connector/abstract.py
romeways/src/core/interfaces/__init__.py
romeways/src/core/interfaces/infrastructure/__init__.py
romeways/src/core/interfaces/infrastructure/queue_connector/__init__.py
romeways/src/core/interfaces/infrastructure/queue_connector/interface.py
romeways/src/core/interfaces/infrastructure/spawner/__init__.py
romeways/src/core/interfaces/infrastructure/spawner/interface.py
romeways/src/core/interfaces/service/__init__.py
romeways/src/core/interfaces/service/chauffeur/__init__.py
romeways/src/core/interfaces/service/chauffeur/interface.py
romeways/src/core/interfaces/service/guide/__init__.py
romeways/src/core/interfaces/service/guide/interface.py
romeways/src/domain/__init__.py
romeways/src/domain/exceptions/__init__.py
romeways/src/domain/exceptions/exception.py
romeways/src/domain/models/__init__.py
romeways/src/domain/models/config/__init__.py
romeways/src/domain/models/config/connector/__init__.py
romeways/src/domain/models/config/connector/model.py
romeways/src/domain/models/config/itinerary/__init__.py
romeways/src/domain/models/config/itinerary/model.py
romeways/src/domain/models/config/map/__init__.py
romeways/src/domain/models/config/map/model.py
romeways/src/domain/models/config/queue/__init__.py
romeways/src/domain/models/config/queue/model.py
romeways/src/domain/models/message/__init__.py
romeways/src/domain/models/message/model.py
romeways/src/infrastructure/__init__.py
romeways/src/infrastructure/spawner/__init__.py
romeways/src/infrastructure/spawner/infrastructure.py
romeways/src/romeways.py
romeways/src/service/__init__.py
romeways/src/service/chauffeur/__init__.py
romeways/src/service/chauffeur/service.py
romeways/src/service/guide/__init__.py
rome_ways-0.2.1.dist-info/LICENSE
rome_ways-0.2.1.dist-info/METADATA
rome_ways-0.2.1.dist-info/WHEEL
rome_ways-0.2.1.dist-info/RECORD
