Metadata-Version: 2.3
Name: rome-ways
Version: 0.2.1
Summary: A queue framework
License: Apache-2.0
Author: Marco Sievers de Almeida Ximit Gaia
Author-email: im.ximit@gmail.com
Requires-Python: >=3.11,<4.0
Classifier: License :: OSI Approved :: Apache Software License
Classifier: Programming Language :: Python :: 3
Classifier: Programming Language :: Python :: 3.11
Classifier: Programming Language :: Python :: 3.12
Classifier: Programming Language :: Python :: 3.13
Provides-Extra: kafka
Provides-Extra: memory
Requires-Dist: meeseeks-singleton (>=0.4.2,<0.5.0)
Requires-Dist: romeways_kafka_queue (>=0.1.0,<0.2.0) ; extra == "kafka"
Requires-Dist: romeways_memory_queue (>=0.2.0,<0.3.0) ; extra == "memory"
Project-URL: documentation, https://github.com/CenturyBoys/romeways
Project-URL: homepage, https://github.com/CenturyBoys/romeways
Project-URL: repository, https://github.com/CenturyBoys/romeways
